CHANGES.rst
CONTRIBUTORS.rst
DEVELOP.rst
LICENSE.rst
MANIFEST.in
README.rst
setup.cfg
setup.py
docs/conf.so
docs/index.rst
src/collective/__init__.py
src/collective.reflex.egg-info/PKG-INFO
src/collective.reflex.egg-info/SOURCES.txt
src/collective.reflex.egg-info/dependency_links.txt
src/collective.reflex.egg-info/entry_points.txt
src/collective.reflex.egg-info/namespace_packages.txt
src/collective.reflex.egg-info/not-zip-safe
src/collective.reflex.egg-info/requires.txt
src/collective.reflex.egg-info/top_level.txt
src/collective/reflex/__init__.py
src/collective/reflex/configure.zcml
src/collective/reflex/events.so
src/collective/reflex/handlers.so
src/collective/reflex/interfaces.pyc
src/collective/reflex/permissions.zcml
src/collective/reflex/report.so
src/collective/reflex/reportpkg.so
src/collective/reflex/setuphandlers.pyc
src/collective/reflex/storage.so
src/collective/reflex/subscribers.so
src/collective/reflex/subscribers.zcml
src/collective/reflex/tasks.so
src/collective/reflex/testing.so
src/collective/reflex/update.so
src/collective/reflex/upgrades.so
src/collective/reflex/upgrades.zcml
src/collective/reflex/utils.so
src/collective/reflex/adapters/__init__.py
src/collective/reflex/adapters/configure.zcml
src/collective/reflex/adapters/helper.so
src/collective/reflex/adapters/template.so
src/collective/reflex/adapters/typing.so
src/collective/reflex/behaviors/__init__.py
src/collective/reflex/behaviors/configure.zcml
src/collective/reflex/behaviors/report_data.pyc
src/collective/reflex/browser/__init__.py
src/collective/reflex/browser/actions.so
src/collective/reflex/browser/configure.zcml
src/collective/reflex/browser/controlpanel.so
src/collective/reflex/browser/form.pyc
src/collective/reflex/browser/generator.so
src/collective/reflex/browser/report_view.so
src/collective/reflex/browser/resource.so
src/collective/reflex/browser/search_view.so
src/collective/reflex/browser/send_pdf.so
src/collective/reflex/browser/serializer.so
src/collective/reflex/browser/upload_file.so
src/collective/reflex/browser/upload_page.so
src/collective/reflex/browser/utils.so
src/collective/reflex/browser/overrides/.gitkeep
src/collective/reflex/browser/static/.gitkeep
src/collective/reflex/browser/static/main.css
src/collective/reflex/browser/static/main.js
src/collective/reflex/browser/static/mark.pdf
